ipdb/__init__.py
ipdb/__main__.py
ipdb/stdout.py
ipdb-0.13.13.dist-info/AUTHORS
ipdb-0.13.13.dist-info/COPYING.txt
ipdb-0.13.13.dist-info/METADATA
ipdb-0.13.13.dist-info/WHEEL
ipdb-0.13.13.dist-info/entry_points.txt
ipdb-0.13.13.dist-info/top_level.txt
ipdb-0.13.13.dist-info/zip-safe
ipdb-0.13.13.dist-info/RECORD
