Metadata-Version: 2.1
Name: ipdb
Version: 0.13.13
Summary: IPython-enabled pdb
Home-page: https://github.com/gotcha/ipdb
Author: Godefroid Chapelle
Author-email: gotcha@bubblenet.be
License: BSD
Keywords: pdb ipython
Classifier: Programming Language :: Python :: 2.7
Classifier: Programming Language :: Python :: 3
Classifier: Programming Language :: Python :: 3.4
Classifier: Programming Language :: Python :: 3.5
Classifier: Programming Language :: Python :: 3.6
Classifier: Programming Language :: Python :: 3.7
Classifier: Programming Language :: Python :: 3.8
Classifier: Programming Language :: Python :: 3.9
Classifier: Programming Language :: Python :: 3.10
Classifier: Programming Language :: Python :: 3.11
Classifier: Operating System :: MacOS :: MacOS X
Classifier: Operating System :: POSIX :: Linux
Classifier: Operating System :: Microsoft :: Windows
Classifier: Topic :: Software Development :: Debuggers
Classifier: License :: OSI Approved :: BSD License
Requires-Python: >=2.7, !=3.0.*, !=3.1.*, !=3.2.*, !=3.3.*
License-File: COPYING.txt
License-File: AUTHORS
